pglt_set_dependencies.py
run_pglt.py
setup.cfg
setup.py
pglt/__init__.py
pglt/dependencies.p
pglt/gene_parameters.csv
pglt/parameters.csv
pglt.egg-info/.DS_Store
pglt.egg-info/PKG-INFO
pglt.egg-info/SOURCES.txt
pglt.egg-info/dependency_links.txt
pglt.egg-info/requires.txt
pglt.egg-info/top_level.txt
pglt/stages/__init__.py
pglt/stages/alignment_stage.py
pglt/stages/download_stage.py
pglt/stages/names_stage.py
pglt/stages/phylogeny_stage.py
pglt/tools/__init__.py
pglt/tools/alignment_tools.py
pglt/tools/download_tools.py
pglt/tools/entrez_tools.py
pglt/tools/names_tools.py
pglt/tools/phylogeny_tools.py
pglt/tools/setup_tools.py
pglt/tools/special_tools.py
pglt/tools/system_tools.py
tests/__init__.py
tests/test_stages_alignment.py
tests/test_stages_download.py
tests/test_stages_names.py
tests/test_stages_phylogeny.py
tests/test_tools_alignment.py
tests/test_tools_download.py
tests/test_tools_entrez.py
tests/test_tools_names.py
tests/test_tools_phylogeny.py
tests/test_tools_setup.py
tests/test_tools_special.py
tests/test_tools_system.py