Metadata-Version: 1.1
Name: pglt
Version: v0.1-beta
Summary: pG-lt: An automated pipeline for phylogeney generation.
Home-page: https://github.com/DomBennett/MassPhylogenyEstimation
Author: Dominic John Bennett
Author-email: dominic.john.bennett@gmail.com
License: LICENSE.txt
Keywords: phylogenetics ecology evolution conservation
Platform: UNKNOWN
Classifier: Development Status :: 4 - Beta
Classifier: Topic :: Scientific/Engineering :: Bio-Informatics
Classifier: Programming Language :: Python :: 2.7
Classifier: License :: OSI Approved :: GNU General Public License v2 (GPLv2)
